FuncPyPipe/FuncPyPipe.py
FuncPyPipe/__init__.py
FuncPyPipe-0.0.3.dist-info/DESCRIPTION.rst
FuncPyPipe-0.0.3.dist-info/METADATA
FuncPyPipe-0.0.3.dist-info/RECORD
FuncPyPipe-0.0.3.dist-info/WHEEL
FuncPyPipe-0.0.3.dist-info/metadata.json
FuncPyPipe-0.0.3.dist-info/top_level.txt
